pc/pc.v
module pc(clk,rst,branch,increment,bra_add,address);
input wire clk,rst,branch,increment;
input wire [15:0] bra_add;
output reg [15:0] address;
always @(rst) begin
    if (rst) begin
        assign address=16'hFFCA;
    end
    else begin 
        deassign address;
    end
end
always @(posedge clk) begin
    if(branch) address=bra_add;
    else if(increment) address=address+1;
    else address=address;
end
endmodule

pc/pc_tb.v
`include "pc.v"
module pc_tb();
reg clk,rst,branch,increment;
reg[15:0] bra_add;
wire[15:0] address;
pc p(clk,rst,branch,increment,bra_add,address);
always #5 clk=~clk;
initial begin
    $dumpfile("tb.vcd");
    $dumpvars(1,p);
    clk=0;
    increment=1;
    #10 rst=1;
    #20 rst=0;
    #40 branch=1;
        bra_add=$random;
    #20
        branch=0;
    #40
        increment=0;
    #50
    $finish;
end
endmodule

pc/tb.vcd
$date
	Mon Jun 10 15:58:24 2024
$end
$version
	Icarus Verilog
$end
$timescale
	1s
$end
$scope module pc_tb $end
$scope module p $end
$var wire 16 ! bra_add [15:0] $end
$var wire 1 " branch $end
$var wire 1 # clk $end
$var wire 1 $ increment $end
$var wire 1 % rst $end
$var reg 16 & address [15:0] $end
$upscope $end
$upscope $end
$enddefinitions $end
#0
$dumpvars
bx &
x%
1$
0#
x"
bx !
$end
#5
1#
#10
b1111111111001010 &
0#
1%
#15
1#
#20
0#
#25
1#
#30
0#
0%
#35
b1111111111001011 &
1#
#40
0#
#45
b1111111111001100 &
1#
#50
0#
#55
b1111111111001101 &
1#
#60
0#
#65
b1111111111001110 &
1#
#70
0#
b11010100100100 !
1"
#75
b11010100100100 &
1#
#80
0#
#85
1#
#90
0#
0"
#95
b11010100100101 &
1#
#100
0#
#105
b11010100100110 &
1#
#110
0#
#115
b11010100100111 &
1#
#120
0#
#125
b11010100101000 &
1#
#130
0#
0$
