alu/adder.v
module adder(a,b,cin,s,cout,over);
input wire cin;
input wire[7:0] a,b;
output wire cout,over;
output wire[7:0] s;
wire c1,c2,c3,cov;
two_bit_adder a1(a[1-:2],b[1-:2],cin,s[1-:2],c1);
two_bit_adder a2(a[3-:2],b[3-:2],c1,s[3-:2],c2);
two_bit_adder a3(a[5-:2],b[5-:2],c2,s[5-:2],c3);
two_bit_adder_ov a4(a[7-:2],b[7-:2],c3,s[7-:2],cout,cov);
assign over=cov^cout;
endmodule

module two_bit_adder(a,b,cin,s,cout);
input wire cin;
input wire[1:0] a,b;
output wire cout;
output wire[1:0] s;
wire c1;
assign s[0]=a[0]^b[0]^cin;
assign c1=(a[0]&b[0])+(a[0]&cin)+(b[0]&cin);
assign s[1]=(a[1]^b[1]^c1);
assign cout=(a[1]&b[1])+((a[0]&a[1]&b[0])+(a[0]&b[0]&b[1])+(a[0]&a[1]&cin)+(a[0]&b[1]&cin)+(a[1]&b[0]&cin)+(b[0]&b[1]&cin));
endmodule

module two_bit_adder_ov(a,b,cin,s,cout,cov);
input wire cin;
input wire[1:0] a,b;
output wire cout,cov;
output wire[1:0] s;

assign s[0]=a[0]^b[0]^cin;
assign cov=(a[0]&b[0])+(a[0]&cin)+(b[0]&cin);
assign s[1]=(a[1]^b[1]^cov);
assign cout=(a[1]&b[1])+((a[0]&a[1]&b[0])+(a[0]&b[0]&b[1])
            +(a[0]&a[1]&cin)+(a[0]&b[1]&cin)+(a[1]&b[0]&cin)
            +(b[0]&b[1]&cin));
endmodule

alu/alu_tb.v
`include "adder.v"
module alu_tb();
reg cin;
reg[7:0] a,b;
wire cout,over;
wire[7:0] s;

adder ad(a,b,cin,s,cout,over);
integer i;
initial begin
    $dumpfile("alu.vcd");
    $dumpvars(1,ad);
        for (i=0;i<10;i=i+1) begin
            cin=$random;
            a=$random;
            b=$random;
            #5;
        end

end
    
endmodule

alu/alu.vcd
$date
	Mon Jun 10 19:55:38 2024
$end
$version
	Icarus Verilog
$end
$timescale
	1s
$end
$scope module alu_tb $end
$scope module ad $end
$var wire 8 ! a [7:0] $end
$var wire 8 " b [7:0] $end
$var wire 1 # cin $end
$var wire 1 $ over $end
$var wire 8 % s [7:0] $end
$var wire 1 & cov $end
$var wire 1 ' cout $end
$var wire 1 ( c3 $end
$var wire 1 ) c2 $end
$var wire 1 * c1 $end
$upscope $end
$upscope $end
$enddefinitions $end
#0
$dumpvars
0*
0)
0(
0'
0&
b10001010 %
0$
0#
b1001 "
b10000001 !
$end
#5
1)
b10011011 %
b10001101 "
b1101 !
1#
#10
1*
b10100 %
0)
b1 "
b10010 !
#15
1$
1&
b10110100 %
1)
1(
b111101 "
b1110110 !
#20
0$
0*
b10000110 %
1)
1(
1&
1'
b11111001 "
b10001100 !
#25
1$
0(
1'
0)
0&
b1101111 %
b10101010 "
b11000101 !
0#
#30
1&
1$
1(
0'
0)
b10001010 %
1*
b10010 "
b1110111 !
1#
#35
0$
1)
1*
b11000001 %
1(
1&
1'
b11001110 "
b11110010 !
#40
1&
1)
0(
1'
0*
b100001 %
b1011100 "
b11000101 !
0#
#45
1$
0'
1)
1(
1&
b10010011 %
b1100101 "
b101101 !
1#
