alu/alu.v
`include "adder.v"
`include "l_shift.v"
`include "r_shift.v"
`include "../mux.v"

module alu(clk,rst,op,accumulator,operand_2,status,result,status_out);
input wire clk,rst;
input wire[3:0] op;
input wire[7:0] accumulator,operand_2,status;
output wire[7:0] result,status_out;

wire[7:0] result_temp_adder,result_temp_sub,status_out_temp_add,status_out_temp_sub,result_temp_bypass;

reg[7:0] alu_sel,operand;

reg cin,sh_r;

//status reg contents : carry zero interrput_disable decimal_mode break_cmd overflow negative

parameter ADD=0,ADC=1,SBC=2,AND=3,EOR=4,ORA=5,BIT=6,ASL=7,LSR=8,ROL=9,ROR=10,PASS=11;
parameter add=7'b0000001,L_shift=7'b0000010,R_shift=7'b0000100,AND_L=7'b0001000,EOR_L=7'b0010000,ORA_L=7'b0100000,BIT_L=7'b1000000;
always @(posedge clk) begin
    case (op)
        ADD: begin
                alu_sel=add;
                cin=0;
                operand=operand_2;
                sh_r=1'bx;
        end
        ADC: begin
                alu_sel=add;
                cin=status[7];
                operand=operand_2;
                sh_r=1'bx;
        end
        SBC: begin
                alu_sel=add;
                cin=1'b1;
                operand=~operand_2;
                sh_r=1'bx;
        end
        AND: begin
                alu_sel=AND_L;
                cin=1'bx;
                operand=operand_2;
                sh_r=1'bx;
        end
        EOR: begin
                alu_sel=EOR_L;
                cin=1'bx;
                operand=operand_2;
                sh_r=1'bx;
        end
        ORA: begin
                alu_sel=ORA_L;
                cin=1'bx;
                operand=operand_2;
                sh_r=1'bx;
        end
        BIT: begin
                alu_sel=BIT_L;
                cin=1'bx;
                operand=operand_2;
                sh_r=1'bx;
        end
        ASL: begin
                alu_sel=L_shift;
                cin=status[7];
                operand=operand_2;
                sh_r=1'b1;
        end
        LSR: begin
                alu_sel=R_shift;
                cin=status[7];
                operand=operand_2;
                sh_r=1'b1;
        end
        ROL: begin
                alu_sel=L_shift;
                cin=status[7];
                operand=operand_2;
                sh_r=1'b0;
        end
        ROR: begin
                alu_sel=R_shift;
                cin=status[7];
                operand=operand_2;
                sh_r=1'b0;
        end
        default: begin
            alu_sel=0;
            operand=operand_2;
            cin=0;
            sh_r=1'bx;
        end
    endcase
end

adder ad(accumulator,operand,cin,alu_sel[0],result_temp_adder,status_out_temp_add[7],status_out_temp_add[1]);
adder ads(result_temp_adder,~{7'd0,status[7]},1'b1,alu_sel[0],result_temp_sub,status_out_temp_sub[7],status_out_temp_sub[1]);
mux_2x1 #(8) m1(alu_sel[0],!(op==SBC),result_temp_adder,result_temp_sub,result_temp_bypass);
mux_2x1 #(8) m2(alu_sel[0],!(op==SBC),status_out_temp_add,status_out_temp_sub,status_out);
l_shift ls(alu_sel[1],sh_r,cin,operand,status_out[7],result_temp_bypass);
r_shift rs(alu_sel[2],sh_r,cin,operand,status_out[7],result_temp_bypass);
and_l an(alu_sel[3],accumulator,operand,result_temp_bypass);
eor_l er(alu_sel[4],accumulator,operand,result_temp_bypass);
ora_l ol(alu_sel[5],accumulator,operand,result_temp_bypass);
bit_l bt(alu_sel[6],accumulator,operand,result_temp_bypass,status_out[1]);

assign result=(op==PASS)?operand_2:result_temp_bypass;

assign status_out[6]=~(|result);
assign status_out[0]=result[7];


endmodule




module and_l (
    en,operand_1,operand_2,result
);

input wire en;
input wire [7:0] operand_1,operand_2;
output wire[7:0] result;

assign result=en?operand_1&operand_2:8'hzz;
    
endmodule

module eor_l (
    en,operand_1,operand_2,result
);

input wire en;
input wire [7:0] operand_1,operand_2;
output wire[7:0] result;

assign result=en?operand_1^operand_2:8'hzz;
    
endmodule

module ora_l (
    en,operand_1,operand_2,result
);

input wire en;
input wire [7:0] operand_1,operand_2;
output wire[7:0] result;

assign result=en?operand_1|operand_2:8'hzz;
    
endmodule

module bit_l (
    en,operand_1,operand_2,result,over
);

input wire en;
input wire [7:0] operand_1,operand_2;
output wire[7:0] result;
output wire over;

assign result=en?operand_1&operand_2:8'hzz;
assign over=en?operand_2[6]:1'bz;
endmodule

alu/r_shift.v
module r_shift(
    en,sh_r,cin,operand,
    cout,result
);
input wire en,sh_r,cin;
input wire[7:0] operand;
output wire[7:0] result;
output wire cout;
wire cout_buff;

wire[7:0] result_buff;

assign {result_buff,cout}=sh_r?{1'b0,operand}:{cin,operand};

assign result=en?result_buff:8'hzz;
assign cout=en?cout_buff:1'bz;


endmodule

alu/l_shift.v
module l_shift(
    clk,en,sh_r,operand,
    cout,result
);
input wire clk,en,sh_r;
input wire[7:0] operand;
output wire[7:0] result;
output wire cout;
reg cout_buff;

reg[7:0] result_buff;

always @(posedge clk ) begin
    cout_buff=operand[7];
    result_buff={operand[6:0],1'b0};
end

assign result=en?result_buff:8'hzz;
assign cout=en?cout_buff:1'bz;


endmodule

mux.v
module mux_8x1 #(parameter width=8) (i0,i1,i2,i3,i4,i5,i6,i7,select,en,out);
input wire en;
input wire[width-1:0] i0,i1,i2,i3,i4,i5,i6,i7;
input wire[2:0] select;
output wire[width-1:0] out;
assign out=en?(select==0)?i0:
            (select==1)?i1:
            (select==2)?i2:
            (select==3)?i3:
            (select==4)?i4:
            (select==5)?i5:
            (select==6)?i6:i7
            :{width{1'bz}};
endmodule

module mux_2x1 #(parameter width=8) (
    en,sel,i0,i1,out
);
input wire sel,en;
input wire[width-1:0] i0,i1;
output wire[width-1:0] out;
assign out=en?sel?i1:i0:{width{1'bz}};
    
endmodule

module mux_4x1 #(parameter width=8) ();

input wire en;
input wire[1:0] sel;
input wire[width-1:0] i0,i1,i2,i3;
output wire[width-1:0] out;
assign out=en? (sel==0?i0:
                sel==1?i1:
                sel==2?i2:i3)
            :{width{1'bz}};
    
endmodule

// module mux_tb();
// reg en;
// reg[7:0] i0,i1,i2,i3,i4,i5,i6,i7;
// reg[2:0] select;
// wire[7:0] out;
// mux_8x1 #(8) m(i0,i1,i2,i3,i4,i5,i6,i7,select,en,out);
// integer i;
// initial begin
//     $dumpfile("mux.vcd");
//     $dumpvars(1,m);
//     i0=$random;
//     i1=$random;
//     i2=$random;
//     i3=$random;
//     i4=$random;
//     i5=$random;
//     i6=$random;
//     i7=$random;
//     en=0;
//     #20
//     en=1;
//     for (i=0;i<8;i=i+1) begin
//         select=i;
//         #20;
//     end 
//     $finish;
// end
// endmodule

alu/adder.v
module adder(en,a_s,a,b,cin,result,cout);
input wire en,a_s,cin;
input wire [7:0] a,b;
output wire cout;
output wire [7:0] result;
assign {cout,result}=en?(a_s?a+b+cin:a-b-cin):9'bz;
endmodule
module full_adder(a_s,a,b,cin,r,cout);
input wire a_s,a,b,cin;
output wire r,cout;
assign r=(a_s?a:~a)^b^cin;
assign cout=(a_s?a:~a)&b|(a_s?a:~a)&cin|b&cin;
endmodule

alu/alu_tb.v
`include "alu.v"

module alu_tb();
reg clk,rst;
reg [3:0] op;
reg [7:0] accumulator,operand_2,status;
wire[7:0] result,status_out;
integer i;

alu al(clk,rst,op,accumulator,operand_2,status,result,status_out);

always #5 clk=~clk;
initial begin
    $dumpfile("alu.vcd");
    $dumpvars(1,al);
    clk=0;
    accumulator=8'd66;
    operand_2=8'd30;
    status=8'b00000000;
    for (i=0;i<12;i=i+1) begin
        op=i;
        #15;
    end
    #15;
    $finish;
end
    
endmodule

alu/alu.vcd
$date
	Tue Jun 18 22:43:40 2024
$end
$version
	Icarus Verilog
$end
$timescale
	1s
$end
$scope module alu_tb $end
$scope module al $end
$var wire 8 ! accumulator [7:0] $end
$var wire 1 " clk $end
$var wire 4 # op [3:0] $end
$var wire 8 $ operand_2 [7:0] $end
$var wire 8 % result_temp_bypass [7:0] $end
$var wire 1 & rst $end
$var wire 8 ' status [7:0] $end
$var wire 8 ( status_out [7:0] $end
$var wire 8 ) status_out_temp_sub [7:0] $end
$var wire 8 * status_out_temp_add [7:0] $end
$var wire 8 + result_temp_sub [7:0] $end
$var wire 8 , result_temp_adder [7:0] $end
$var wire 8 - result [7:0] $end
$var reg 8 . alu_sel [7:0] $end
$var reg 1 / cin $end
$var reg 8 0 operand [7:0] $end
$var reg 1 1 sh_r $end
$upscope $end
$upscope $end
$enddefinitions $end
#0
$dumpvars
x1
bx 0
x/
bx .
bx -
bx ,
bx +
bxzzzzzxz *
bxzzzzzxz )
bxzzzzxx (
b0 '
x&
bx %
b11110 $
b0 #
0"
b1000010 !
$end
#5
bx0zzzz00 (
b1100000 -
b1zzzzz0z )
b1100000 %
b1100000 +
b1100000 ,
b0zzzzz0z *
b11110 0
0/
b1 .
1"
#10
0"
#15
1"
b1 #
#20
0"
#25
1"
#30
b0zzzz00 (
0"
b10 #
#35
b100100 +
b1zzzzz0z *
b100100 -
b100100 %
b100100 ,
b10zzzz00 (
b11100001 0
1/
1"
#40
0"
#45
b10 -
bz ,
bz *
bz +
bz )
b0zzzzz0 (
b10 %
b11110 0
x/
b1000 .
1"
b11 #
#50
0"
#55
1"
#60
0"
b100 #
#65
b1011100 -
b1011100 %
b10000 .
1"
#70
0"
#75
b1011110 -
b1011110 %
b100000 .
1"
b101 #
#80
0"
#85
1"
#90
0"
b110 #
#95
b10 -
b10 %
b0zzzz00 (
b1000000 .
1"
#100
0"
#105
b111100 -
b111100 %
b0zzzzz0 (
11
0/
b10 .
1"
b111 #
#110
0"
#115
1"
#120
0"
b1000 #
#125
b1111 -
b1111 %
b100 .
1"
#130
0"
#135
b111100 -
b111100 %
01
b10 .
1"
b1001 #
#140
0"
#145
1"
#150
0"
b1010 #
#155
b1111 -
b1111 %
b100 .
1"
#160
0"
#165
bz %
x1
b0 .
b11110 -
1"
b1011 #
