clk_gen/clk_gen.v
module clk_gen (
    clk,rst,
    clk_1,clk_2
);

input wire clk,rst;
output wire clk_1,clk_2;

reg[1:0] counter;

always @(posedge clk,posedge rst) begin
    if(rst) counter=0;
    else  counter=counter+1;
end
assign clk_1=counter==0?1:0;
assign clk_2=counter==2?1:0;
endmodule

clk_gen/clkgen_tb.v
`include "clk_gen.v"

module clkgen_tb();
reg clk,rst;
wire clk_1,clk_2;

clk_gen cg(clk,rst,clk_1,clk_2);
always #5 clk=~clk;
initial begin
    $dumpfile("clkgen.vcd");
    $dumpvars(1,cg);
    clk=0;
    #2;
    rst=1;
    #15
    rst=0;
    #100
    $finish;
end   
endmodule

clk_gen/clkgen.vcd
$date
	Tue Jun 18 14:10:00 2024
$end
$version
	Icarus Verilog
$end
$timescale
	1s
$end
$scope module clkgen_tb $end
$scope module cg $end
$var wire 1 ! clk $end
$var wire 1 " rst $end
$var wire 1 # clk_2 $end
$var wire 1 $ clk_1 $end
$var reg 2 % counter [1:0] $end
$upscope $end
$upscope $end
$enddefinitions $end
#0
$dumpvars
bx %
x$
x#
x"
0!
$end
#2
1$
0#
b0 %
1"
#5
1!
#10
0!
#15
1!
#17
0"
#20
0!
#25
0$
b1 %
1!
#30
0!
#35
1#
b10 %
1!
#40
0!
#45
0#
b11 %
1!
#50
0!
#55
1$
b0 %
1!
#60
0!
#65
0$
b1 %
1!
#70
0!
#75
1#
b10 %
1!
#80
0!
#85
0#
b11 %
1!
#90
0!
#95
1$
b0 %
1!
#100
0!
#105
0$
b1 %
1!
#110
0!
#115
1#
b10 %
1!
